{"Three meals a day":{"0":"Korean Restaurant","1":"12 Chun Tin Road Singapore 599599","2":"Reg.No 201505894W","3":null,"4":"Table: 203 9 Pax: 8","5":"Date : 2023-05-24 20:07","6":"Receipt.No.: 2205240061","7":"Description Qty Price","8":"Kalguksu 1 $ 13.00","9":"Dolsot Bibimbap(Beef) 1 $ 13.00","10":"Tteokbokki 1 $ 10.00","11":"Kimchi Pancake 1 $ 17.00","12":"Beef Bulgogi 1 $1300","13":"add Rice 1 $ 2.00","14":"Jjajang Myeon 1 $ 13.00","15":"Chicken Gangjung(M) 1 $ 25.00","16":"Suyebi( Seafood) 1 $ 13.00","17":"Sub Total $ 119.00","18":"Service Charge (10%) $11.90","19":"GST (8%) \u00b0 $ 10.47","20":"Grand Total : \u00a7 141.37","21":null,"22":"\u201cPaid by\"","23":"CASH \u00a9 $ 141.37","24":null,"25":"AARPREAAARARALARABABRARAAAAAAARAAKAAAAAAAKAAKARANAKAAD","26":null,"27":"Reservation Tel No 6463-2346","28":"Welcome and See you Again |","29":null,"30":"APPARARRARRERA SARA RAE","31":"APAAAARAMARAAREAAAARAARARAAY","32":null,"33":"\u00b0","34":null,"35":null}}